CHANGES.rst
CONTRIBUTORS.rst
DEVELOP.rst
LICENSE.GPL
LICENSE.rst
MANIFEST.in
README.rst
requirements.txt
setup.cfg
setup.py
docs/index.rst
src/collective/__init__.py
src/collective.faceted.datewidget.egg-info/PKG-INFO
src/collective.faceted.datewidget.egg-info/SOURCES.txt
src/collective.faceted.datewidget.egg-info/dependency_links.txt
src/collective.faceted.datewidget.egg-info/entry_points.txt
src/collective.faceted.datewidget.egg-info/namespace_packages.txt
src/collective.faceted.datewidget.egg-info/not-zip-safe
src/collective.faceted.datewidget.egg-info/requires.txt
src/collective.faceted.datewidget.egg-info/top_level.txt
src/collective/faceted/__init__.py
src/collective/faceted/datewidget/__init__.py
src/collective/faceted/datewidget/configure.zcml
src/collective/faceted/datewidget/locales/collective.faceted.datewidget.pot
src/collective/faceted/datewidget/locales/update.sh
src/collective/faceted/datewidget/locales/fr/LC_MESSAGES/collective.faceted.datewidget.mo
src/collective/faceted/datewidget/locales/fr/LC_MESSAGES/collective.faceted.datewidget.po
src/collective/faceted/datewidget/range/__init__.py
src/collective/faceted/datewidget/range/configure.zcml
src/collective/faceted/datewidget/range/range.pt
src/collective/faceted/datewidget/range/range.py