Metadata-Version: 2.1
Name: collective.faceted.datewidget
Version: 1.0.1
Summary: Custom date widgets for eea.facetednavigation
Home-page: https://pypi.python.org/pypi/collective.faceted.datewidget
Author: Martin Peeters
Author-email: martin.peeters@affinitic.be
License: GPL version 2
Keywords: Python Plone
Classifier: Environment :: Web Environment
Classifier: Framework :: Plone
Classifier: Framework :: Plone :: 4.3
Classifier: Programming Language :: Python
Classifier: Programming Language :: Python :: 2.7
Classifier: Operating System :: OS Independent
Classifier: License :: OSI Approved :: GNU General Public License v2 (GPLv2)
Provides-Extra: test
License-File: LICENSE.GPL
License-File: LICENSE.rst
